MANIFEST.in
README.md
VERSION
setup.py
friendsreco/__init__.py
friendsreco/api.py
friendsreco/app.py
friendsreco/controller.py
friendsreco/domain.py
friendsreco/exceptions.py
friendsreco/logger.py
friendsreco/openapi.yaml
friendsreco/repository.py
friendsreco/run.py
friendsreco/service.py
friendsreco.egg-info/PKG-INFO
friendsreco.egg-info/SOURCES.txt
friendsreco.egg-info/dependency_links.txt
friendsreco.egg-info/entry_points.txt
friendsreco.egg-info/requires.txt
friendsreco.egg-info/top_level.txt
friendsreco/cypher/compute_recommendations.cypher
friendsreco/cypher/get_friendships.cypher
friendsreco/cypher/get_person_friendships.cypher
friendsreco/cypher/get_person_recommendations.cypher
friendsreco/cypher/get_recommendations.cypher
friendsreco/cypher/make_friendship.cypher
friendsreco/data/friendships.csv