Metadata-Version: 1.1
Name: friendsreco
Version: 0.0.11
Summary: A simple HTTP friends recommendations service.
Home-page: https://github.com/dutradda/friendsreco
Author: Diogo Dutra
Author-email: diogodutradamata@gmail.com
License: MIT
Keywords: recomendations service graph neo4j
Platform: UNKNOWN
Classifier: License :: OSI Approved :: MIT License
Classifier: Programming Language :: Python
Classifier: Programming Language :: Python :: 3.7
Classifier: Development Status :: 3 - Alpha
Classifier: Intended Audience :: Developers
Classifier: Topic :: Internet :: WWW/HTTP
